hyram/README.md
hyram/__init__.py
hyram/phys/__init__.py
hyram/phys/_comps.py
hyram/phys/_flame.py
hyram/phys/_fuel_props.py
hyram/phys/_indoor_release.py
hyram/phys/_jet.py
hyram/phys/_layer.py
hyram/phys/_notional_nozzle.py
hyram/phys/_overpressure_data.py
hyram/phys/_plots.py
hyram/phys/_therm.py
hyram/phys/_unconfined_overpressure.py
hyram/phys/_utils.py
hyram/phys/api.py
hyram/qra/__init__.py
hyram/qra/analysis.py
hyram/qra/component.py
hyram/qra/component_failure.py
hyram/qra/consequence.py
hyram/qra/effects.py
hyram/qra/event_tree.py
hyram/qra/ignition_probs.py
hyram/qra/pipe_size.py
hyram/qra/probits.py
hyram/qra/risk.py
hyram/qra/uncertainty.py
hyram/qra/defaults/__init__.py
hyram/qra/defaults/component_counts.py
hyram/qra/defaults/component_leak_frequencies.py
hyram/qra/defaults/dispenser_failures.py
hyram/qra/uq/__init__.py
hyram/qra/uq/distributions.py
hyram/qra/uq/parallel_evaluations.py
hyram/qra/uq/sampling.py
hyram/utilities/__init__.py
hyram/utilities/custom_warnings.py
hyram/utilities/misc_utils.py
hyram-6.1.dist-info/licenses/COPYING.txt
hyram-6.1.dist-info/METADATA
hyram-6.1.dist-info/WHEEL
hyram-6.1.dist-info/top_level.txt
hyram-6.1.dist-info/RECORD
