Metadata-Version: 2.4
Name: hyram
Version: 6.1
Summary: Hydrogen Plus Other Alternative Fuels Risk Assessment Models Python Package
Author: Erin E. Carrier, Michael C. Devin, Brian D. Ehrhart, Isaac W. Ekoto, Katrina M. Groth, Ethan S. Hecht, Benjamin R. Liu, Alice Muna, John T. Reynolds, Benjamin B. Schroeder, Cianan Sims, Greg Walkup
Maintainer: Michael C. Devin, Brian D. Ehrhart, Ethan S. Hecht, Benjamin R. Liu, Cianan Sims
License-Expression: GPL-3.0-only
Project-URL: homepage, https://hyram.sandia.gov/
Project-URL: repository, https://github.com/sandialabs/hyram
Keywords: hydrogen,methane,propane,flame,plume,jet,overpressure,quantitative risk assessment,risk
Classifier: Development Status :: 5 - Production/Stable
Classifier: Programming Language :: Python :: 3 :: Only
Requires-Python: >=3.9
License-File: COPYING.txt
Requires-Dist: matplotlib>=3.8
Requires-Dist: numpy
Requires-Dist: scipy
Requires-Dist: coolprop>=6.3
Requires-Dist: contourpy
Dynamic: license-file
